sarhash-0.1.0.dist-info/METADATA
sarhash-0.1.0.dist-info/WHEEL
sarhash-0.1.0.dist-info/licenses/LICENSE
sarhash/__init__.py
sarhash/__init__.pyi
sarhash/_sarhash.cpython-311-darwin.so
sarhash/py.typed
sarhash-0.1.0.dist-info/RECORD
