Metadata-Version: 2.4
Name: sarhash
Version: 0.1.0
Classifier: Programming Language :: Rust
Classifier: Programming Language :: Python :: Implementation :: CPython
Classifier: Programming Language :: Python :: Implementation :: PyPy
Classifier: Programming Language :: Python :: 3
Classifier: Programming Language :: Python :: 3.11
Classifier: Programming Language :: Python :: 3.12
Classifier: License :: OSI Approved :: MIT License
Classifier: Development Status :: 4 - Beta
Classifier: Intended Audience :: Developers
Classifier: Topic :: Security :: Cryptography
Requires-Dist: mypy>=1.0 ; extra == 'dev'
Requires-Dist: pytest>=7.0 ; extra == 'dev'
Requires-Dist: black>=23.0 ; extra == 'dev'
Requires-Dist: ruff>=0.1.0 ; extra == 'dev'
Provides-Extra: dev
License-File: LICENSE
Summary: Fast password hashing library powered by Rust
Requires-Python: >=3.11
Project-URL: Homepage, https://github.com/3sarojbhattarai/sarhash
Project-URL: Repository, https://github.com/3sarojbhattarai/sarhash
